tpdataset/__init__.py
tpdataset/dataset.py
tpdataset/device.py
tpdataset/download_googledrive.py
tpdataset/raw_dataset.py
tpdataset/CV/__init__.py
tpdataset/CV/celeba.py
tpdataset/CV/mnist.py
tpdataset/NLP/__init__.py
tpdataset/NLP/babi.py
tpdataset-0.0.38.dist-info/METADATA
tpdataset-0.0.38.dist-info/WHEEL
tpdataset-0.0.38.dist-info/top_level.txt
tpdataset-0.0.38.dist-info/RECORD
