Metadata-Version: 2.1
Name: tpdataset
Version: 0.0.38
Summary: This is A foundamental package containing some basic self-designed functions and types for Project PyCTLib. 
Home-page: https://github.com/Bertie97/pyctlib/tree/main/pyctlib
Author: All contributors of PyCTLib
Author-email: zytfdu@icloud.com
License: MIT Licence
Keywords: pip,pyctlib
Platform: any
Requires-Dist: pyctlib
Requires-Dist: torchplus
Requires-Dist: requests
